MANIFEST.in
README.rst
setup.cfg
setup.py
PyRect.egg-info/PKG-INFO
PyRect.egg-info/SOURCES.txt
PyRect.egg-info/dependency_links.txt
PyRect.egg-info/top_level.txt
docs/Makefile
docs/conf.py
docs/index.rst
docs/make.bat
docs/modules.rst
docs/pyrect.rst
docs/roadmap.rst
pyrect/__init__.py
tests/test_pyrect.py